poetry_plugin_deps_juice/__init__.py
poetry_plugin_deps_juice/command.py
poetry_plugin_deps_juice/plugins.py
poetry_plugin_deps_juice-0.0.3.dist-info/LICENSE
poetry_plugin_deps_juice-0.0.3.dist-info/METADATA
poetry_plugin_deps_juice-0.0.3.dist-info/WHEEL
poetry_plugin_deps_juice-0.0.3.dist-info/entry_points.txt
poetry_plugin_deps_juice-0.0.3.dist-info/RECORD
