Metadata-Version: 2.1
Name: poetry-plugin-deps-juice
Version: 0.0.3
Summary: Poetry plugin for simple mix dependencies from toml option and wrap poetry 'build' command.
License: Apache 2.0
Author: BlackCatDevel0per
Author-email: bcdev@mail.ru
Requires-Python: >=3.8,<4.0
Classifier: Development Status :: 5 - Production/Stable
Classifier: Environment :: Console
Classifier: Intended Audience :: Developers
Classifier: Intended Audience :: Information Technology
Classifier: Intended Audience :: System Administrators
Classifier: License :: OSI Approved :: Apache Software License
Classifier: License :: Other/Proprietary License
Classifier: Operating System :: OS Independent
Classifier: Programming Language :: Python :: 3
Classifier: Programming Language :: Python :: 3.8
Classifier: Programming Language :: Python :: 3.9
Classifier: Programming Language :: Python :: 3.10
Classifier: Programming Language :: Python :: 3.11
Classifier: Programming Language :: Python :: 3.12
Classifier: Programming Language :: Python :: 3.13
Classifier: Topic :: Software Development
Classifier: Topic :: Software Development :: Libraries
Classifier: Topic :: Software Development :: Libraries :: Application Frameworks
Classifier: Topic :: Software Development :: Libraries :: Python Modules
Requires-Dist: build (>=1.0.3,<2.0.0)
Requires-Dist: poetry (>=1.8.0,<2.0.0)
Requires-Dist: poetry-core (>=1.7.0,<2.0.0)
Requires-Dist: setuptools (>=69.0.3,<70.0.0)
Requires-Dist: wheel (>=0.42.0,<0.43.0)
Project-URL: Documentation, https://github.com/BlackCatDevel0per/poetry-plugin-deps-juice
Project-URL: Homepage, https://github.com/BlackCatDevel0per/poetry-plugin-deps-juice
Project-URL: Repository, https://github.com/BlackCatDevel0per/poetry-plugin-deps-juice
